pa11ycrawler/__init__.py
pa11ycrawler/html.py
pa11ycrawler/items.py
pa11ycrawler/settings.py
pa11ycrawler/util.py
pa11ycrawler/commands/__init__.py
pa11ycrawler/commands/test.py
pa11ycrawler/pipelines/__init__.py
pa11ycrawler/pipelines/pa11y.py
pa11ycrawler/spiders/__init__.py
pa11ycrawler/spiders/edx.py
pa11ycrawler/templates/base.html
pa11ycrawler/templates/detail.html
pa11ycrawler/templates/index.html
pa11ycrawler/templates/unique.html
pa11ycrawler/templates/assets/css/bootstrap-table.css
pa11ycrawler/templates/assets/css/bootstrap-table.min.css
pa11ycrawler/templates/assets/css/bootstrap-theme.css
pa11ycrawler/templates/assets/css/bootstrap-theme.css.map
pa11ycrawler/templates/assets/css/bootstrap-theme.min.css
pa11ycrawler/templates/assets/css/bootstrap-theme.min.css.map
pa11ycrawler/templates/assets/css/bootstrap.css
pa11ycrawler/templates/assets/css/bootstrap.css.map
pa11ycrawler/templates/assets/css/bootstrap.min.css
pa11ycrawler/templates/assets/css/bootstrap.min.css.map
pa11ycrawler/templates/assets/js/bootstrap-table-locale-all.js
pa11ycrawler/templates/assets/js/bootstrap-table-locale-all.min.js
pa11ycrawler/templates/assets/js/bootstrap-table.js
pa11ycrawler/templates/assets/js/bootstrap-table.min.js
pa11ycrawler/templates/assets/js/bootstrap.js
pa11ycrawler/templates/assets/js/bootstrap.min.js
pa11ycrawler/templates/assets/js/jquery.js
pa11ycrawler/templates/assets/js/jquery.min.js
pa11ycrawler/templates/assets/js/jquery.min.map
pa11ycrawler/templates/assets/js/jquery.slim.js
pa11ycrawler/templates/assets/js/jquery.slim.min.js
pa11ycrawler/templates/assets/js/jquery.slim.min.map
pa11ycrawler-1.7.3.dist-info/LICENSE
pa11ycrawler-1.7.3.dist-info/METADATA
pa11ycrawler-1.7.3.dist-info/WHEEL
pa11ycrawler-1.7.3.dist-info/entry_points.txt
pa11ycrawler-1.7.3.dist-info/top_level.txt
pa11ycrawler-1.7.3.dist-info/RECORD
