Metadata-Version: 2.1
Name: pa11ycrawler
Version: 1.7.3
Summary: A Scrapy spider for a11y auditing Open edX installations.
Home-page: https://github.com/edx/pa11ycrawler
Author: edX
Author-email: oscm@edx.org
License: Apache-2.0
Platform: UNKNOWN
Classifier: Development Status :: 5 - Production/Stable
Classifier: Environment :: Console
Classifier: Intended Audience :: Developers
Classifier: License :: OSI Approved :: Apache Software License
Classifier: Operating System :: OS Independent
Classifier: Programming Language :: Python
Classifier: Programming Language :: Python :: 2
Classifier: Programming Language :: Python :: 2.7
Classifier: Programming Language :: Python :: 3
Classifier: Programming Language :: Python :: 3.5
Classifier: Programming Language :: Python :: 3.6
Classifier: Programming Language :: Python :: Implementation :: CPython
Classifier: Programming Language :: Python :: Implementation :: PyPy
Classifier: Topic :: Software Development :: Testing
Classifier: Topic :: Software Development :: Quality Assurance
Requires-Dist: Jinja2 (<3.0)
Requires-Dist: lxml (<4.0)
Requires-Dist: path.py (<9.0)
Requires-Dist: pyyaml
Requires-Dist: requests (<3.0)
Requires-Dist: scrapy (==1.6.0)
Requires-Dist: urlobject (<3.0)
Requires-Dist: pytest-cov (>=2.4.0)
